messengers_loggers/__init__.py
messengers_loggers/slack/__init__.py
messengers_loggers/telegram/__init__.py
messengers_loggers/telegram/formatters.py
messengers_loggers/telegram/handlers.py
messengers_loggers/utils/__init__.py
messengers_loggers/utils/html.py
messengers_loggers/vk/__init__.py
messengers_loggers-0.1.4.dist-info/LICENSE
messengers_loggers-0.1.4.dist-info/WHEEL
messengers_loggers-0.1.4.dist-info/METADATA
messengers_loggers-0.1.4.dist-info/RECORD
