Metadata-Version: 2.1
Name: messengers-loggers
Version: 0.1.4
Summary: Loggers for sending log to messengers
License: Apache-2.0 License
Author: arck1
Author-email: a.v.rakhimov@gmail.com
Requires-Python: >=3.8,<4.0
Classifier: License :: Other/Proprietary License
Classifier: Programming Language :: Python :: 3
Classifier: Programming Language :: Python :: 3.8
Classifier: Programming Language :: Python :: 3.9
Provides-Extra: test
Requires-Dist: pytest (>=5.4.3,<6.0.0); extra == "test"
Requires-Dist: requests (>=2.25.1,<3.0.0)
